ttdays/__init__.py
ttdays/date_calculator.py
ttdays/date_model.py
ttdays/functions.py
ttdays-0.1.1.dist-info/METADATA
ttdays-0.1.1.dist-info/WHEEL
ttdays-0.1.1.dist-info/licenses/LICENSE
ttdays-0.1.1.dist-info/RECORD
