Metadata-Version: 2.4
Name: ttdays
Version: 0.1.1
Summary: A tool that calculates how many days have passed between a given start date (e.g., a person's birthday or a company's founding date) and an end date (e.g., today), or determines a specific date based on a start date and a number of elapsed days (e.g., what date it will be on the 10000th day since birth).
Author-email: well-living <your@email.com>
License: MIT
License-File: LICENSE
Requires-Python: >=3.12
Requires-Dist: pydantic
Provides-Extra: dev
Requires-Dist: pre-commit; extra == 'dev'
Requires-Dist: pytest; extra == 'dev'
Requires-Dist: pytest-cov; extra == 'dev'
Requires-Dist: ruff; extra == 'dev'
